cyber_wiz_api.py
exception.py
cyber_wiz_email_client-0.0.2.dist-info/METADATA
cyber_wiz_email_client-0.0.2.dist-info/WHEEL
cyber_wiz_email_client-0.0.2.dist-info/top_level.txt
cyber_wiz_email_client-0.0.2.dist-info/RECORD
