Metadata-Version: 2.1
Name: cyber-wiz-email-client
Version: 0.0.2
Summary: Client to communicate with email cyber-wiz
Home-page: https://gitlab.com/aswin.cv/cyber-wiz-email-client
Author: Cyber Wiz
Author-email: info@cyber-wiz.com
License: unlicense
Platform: UNKNOWN
Requires-Dist: requests
